[{
  "_id": {
    "$oid": "5f987a8bd1298b6768b78112"
  },
  "name": "Feira da música de fortaleza",
  "title_key": "feira-da-musica-fortaleza",
  "sympla_id": "1021149",
  "sympla_url": "https://www.sympla.com.br/projeto-feira-copia__1021149",
  "tickets": [
    {
      "$oid": "111111111111111111111111"
    }
  ],
  "description": "Mussum Ipsum, cacilds vidis litro abertis. Aenean aliquam molestie leo, vitae iaculis nisl. Copo furadis é disculpa de bebadis, arcu quam euismod magna. Manduma pindureta quium dia nois paga. Mais vale um bebadis conhecidiss, que um alcoolatra anonimis.",
  "tags": ["música", "oficinas", "mostra de video clipe", "hackaton", "zona de propulsão"],
  "image_url" :"https://oasi-assets.s3-us-west-2.amazonaws.com/feira-logo.png",
  "cover_url": "https://oasi-assets.s3-us-west-2.amazonaws.com/feira-bg.png",
  "end_date": "2020-11-13T23:59:59.000Z",
  "start_date": "2020-11-11T00:00:00.000Z",
  "is_free": true,
  "status": "ACTIVE",
  "productor": {
    "$oid": "111111111111111111111111"
  },
  "activities": [
    {
      "$oid": "5f987a8bd1298b6768b78001"
    },
    {
      "$oid": "5f987a8bd1298b6768b78011"
    },
    {
      "$oid": "5f987a8bd1298b6768b78012"
    },
    {
      "$oid": "5f987a8bd1298b6768b78013"
    }
  ]
},
{
  "_id": {
    "$oid": "5f987a92d1298b6768b78113"
  },
  "name": "Evento 02",
  "title_key": "evento-02",
  "sympla_id": "sympla_id_02",
  "sympla_url": "https://www.sympla.com.br/projeto-feira-copia__1021149",
  "tickets": [
    {
      "$oid": "222222222222222222222222"
    }
  ],
  "description": "Mussum Ipsum, cacilds vidis litro abertis. Aenean aliquam molestie leo, vitae iaculis nisl. Copo furadis é disculpa de bebadis, arcu quam euismod magna. Manduma pindureta quium dia nois paga. Mais vale um bebadis conhecidiss, que um alcoolatra anonimis.",
  "tags": ["música", "oficinas", "mostra de video clipe", "hackaton", "zona de propulsão"],
  "image_url" :"https://images.vexels.com/media/users/3/156818/isolated/preview/dd5e2a6e56180b587a71109957211e2e---cone-de-mala-de-bagagem-by-vexels.png",
  "cover_url" :"https://i.pinimg.com/originals/80/bf/a1/80bfa10f9b115a37fc3202243bf509db.png",
  "end_date": "2020-11-24T23:00:00.000Z",
  "start_date": "2020-11-24T23:00:00.000Z",
  "is_free": false,
  "status": "ACTIVE",
  "productor": {
    "$oid": "222222222222222222222222"
  },
  "activities": [
    {
      "$oid": "5f987a8bd1298b6768b78002"
    }
  ]
},
{
  "_id": {
    "$oid": "5f987a92d1398b6768b78114"
  },
  "name": "Evento 03",
  "title_key": "evento-03",
  "sympla_id": "sympla_id_03",
  "sympla_url": "https://www.sympla.com.br/projeto-feira-copia__1021149",
  "tickets": [
    {
      "$oid": "333333333333333333333333"
    }
  ],
  "description": "Mussum Ipsum, cacilds vidis litro abertis. Aenean aliquam molestie leo, vitae iaculis nisl. Copo furadis é disculpa de bebadis, arcu quam euismod magna. Manduma pindureta quium dia nois paga. Mais vale um bebadis conhecidiss, que um alcoolatra anonimis.",
  "tags": ["música", "oficinas", "mostra de video clipe", "hackaton", "zona de propulsão"],
  "image_url" :"https://images.vexels.com/media/users/3/156818/isolated/preview/dd5e2a6e56180b587a71109957211e2e---cone-de-mala-de-bagagem-by-vexels.png",
  "cover_url" :"https://c4.wallpaperflare.com/wallpaper/68/58/339/anime-inuyasha-inuyasha-character-wallpaper-preview.jpg",
  "end_date": "2020-12-04T23:00:00.000Z",
  "start_date": "2020-12-03T23:00:00.000Z",
  "is_free": false,
  "status": "ACTIVE",
  "productor": {
    "$oid": "222222222222222222222222"
  },
  "activities": [
    {
      "$oid": "5f987a8bd1298b6768b78003"
    }
  ]
}


]